{
  "updated": "2026-05-04",
  "image_date": "2 May 2026",
  "commentary": {
    "en": "The equatorial Pacific displays a clear La Niña pattern with extensive cool anomalies (-2 to -3°C) across the central and eastern tropical Pacific, while warmer waters persist in the western Pacific warm pool. Significant marine heatwave conditions (+2 to +4°C) are evident across much of the North Pacific, including waters around Japan and extending toward the Coral Triangle region, creating elevated thermal stress risks for coral reefs in Okinawa and the broader western Pacific. The Atlantic Ocean also shows widespread warming anomalies, particularly in the Caribbean and tropical Atlantic where coral reef systems may face bleaching stress.",
    "ja": "赤道太平洋では明確なラニーニャパターンが見られ、中部・東部熱帯太平洋で広範囲な低温偏差（-2〜-3°C）が観測される一方、西太平洋暖水域では高温が持続している。北太平洋の大部分で顕著な海洋熱波状態（+2〜+4°C）が確認され、日本周辺からコーラルトライアングル地域にかけて広がっており、沖縄や西太平洋全域のサンゴ礁に高い熱ストレスリスクをもたらしている。大西洋でも広範囲で昇温偏差が見られ、特にカリブ海や熱帯大西洋ではサンゴ礁システムが白化ストレスに直面する可能性がある。"
  }
}