{
  "updated": "2026-02-16",
  "image_date": "14 Feb 2026",
  "commentary": {
    "en": "The equatorial Pacific displays a La Niña pattern with cooler than normal waters extending from the central to eastern Pacific, while warmer anomalies persist in the western Pacific warm pool. Elevated temperatures across the Coral Triangle, northern Australia, and waters surrounding Japan create concerning conditions for coral reef ecosystems in these biodiversity hotspots. Notable marine heatwave conditions are evident in the North Pacific, particularly around Japan and extending toward the Bering Sea, alongside warm anomalies in parts of the Indian Ocean.",
    "ja": "赤道太平洋では中部から東部にかけて平年より低い海水温が広がるラニーニャパターンが見られ、一方で西太平洋暖水域では高温偏差が持続している。コーラルトライアングル、オーストラリア北部、日本周辺海域で海水温の上昇が確認され、これらの生物多様性ホットスポットのサンゴ礁生態系にとって懸念される状況となっている。北太平洋、特に日本周辺からベーリング海方面、およびインド洋の一部海域で顕著な海洋熱波状態が観測されている。"
  }
}